multiping.py
multiping.py-1.4.1.dist-info/LICENSE
multiping.py-1.4.1.dist-info/METADATA
multiping.py-1.4.1.dist-info/WHEEL
multiping.py-1.4.1.dist-info/entry_points.txt
multiping.py-1.4.1.dist-info/top_level.txt
multiping.py-1.4.1.dist-info/RECORD
