Metadata-Version: 2.1
Name: multiping.py
Version: 1.4.1
Summary: ncurses frontend to ping
Home-page: https://github.com/mgedmin/multiping
Author: Marius Gedminas
Author-email: marius@gedmin.as
License: GPL v2 or v3
Project-URL: Changelog, https://github.com/mgedmin/multiping/blob/master/CHANGES.rst
Keywords: ping ncurses
Classifier: Development Status :: 5 - Production/Stable
Classifier: Environment :: Console
Classifier: Environment :: Console :: Curses
Classifier: Intended Audience :: System Administrators
Classifier: License :: OSI Approved :: GNU General Public License v2 (GPLv2)
Classifier: License :: OSI Approved :: GNU General Public License v3 (GPLv3)
Classifier: Operating System :: POSIX
Classifier: Operating System :: Microsoft :: Windows
Classifier: Programming Language :: Python
Classifier: Programming Language :: Python :: 3.7
Classifier: Programming Language :: Python :: 3.8
Classifier: Programming Language :: Python :: 3.9
Classifier: Programming Language :: Python :: 3.10
Classifier: Programming Language :: Python :: 3.11
Classifier: Programming Language :: Python :: 3.12
Classifier: Programming Language :: Python :: 3.13
Classifier: Programming Language :: Python :: Implementation :: CPython
Classifier: Programming Language :: Python :: Implementation :: PyPy
Requires-Python: >=3.7
License-File: LICENSE
Requires-Dist: windows-curses; platform_system == "Windows"
Provides-Extra: test
Requires-Dist: mock; extra == "test"
